freezy/__init__.py
freezy/extractor.py
freezy/filter.py
freezy/freeze.py
freezy/speed.py
freezy-1.3.0.dist-info/LICENSE
freezy-1.3.0.dist-info/METADATA
freezy-1.3.0.dist-info/WHEEL
freezy-1.3.0.dist-info/top_level.txt
freezy-1.3.0.dist-info/RECORD
